jac_client/examples/all-in-one/button.jac
jac_client/examples/all-in-one/main.jac
jac_client/examples/all-in-one/assets/workers/worker.py
jac_client/examples/all-in-one/components/CategoryFilter.jac
jac_client/examples/all-in-one/components/Header.jac
jac_client/examples/all-in-one/components/ProfitOverview.jac
jac_client/examples/all-in-one/components/Summary.jac
jac_client/examples/all-in-one/components/TransactionForm.jac
jac_client/examples/all-in-one/components/TransactionItem.jac
jac_client/examples/all-in-one/components/TransactionList.jac
jac_client/examples/all-in-one/components/button.jac
jac_client/examples/all-in-one/components/navigation.jac
jac_client/examples/all-in-one/constants/categories.jac
jac_client/examples/all-in-one/constants/clients.jac
jac_client/examples/all-in-one/context/BudgetContext.jac
jac_client/examples/all-in-one/hooks/useBudget.jac
jac_client/examples/all-in-one/hooks/useLocalStorage.jac
jac_client/examples/all-in-one/pages/BudgetPlanner.jac
jac_client/examples/all-in-one/pages/FeaturesTest.jac
jac_client/examples/all-in-one/pages/LandingPage.jac
jac_client/examples/all-in-one/pages/budget_planner_ui.cl.jac
jac_client/examples/all-in-one/pages/features_test_ui.cl.jac
jac_client/examples/all-in-one/pages/loginPage.jac
jac_client/examples/all-in-one/pages/nestedDemo.jac
jac_client/examples/all-in-one/pages/notFound.jac
jac_client/examples/all-in-one/pages/signupPage.jac
jac_client/examples/all-in-one/utils/formatters.jac
jac_client/examples/asset-serving/css-with-image/main.jac
jac_client/examples/asset-serving/image-asset/main.jac
jac_client/examples/asset-serving/import-alias/main.jac
jac_client/examples/basic/main.jac
jac_client/examples/basic-auth/main.jac
jac_client/examples/basic-auth-with-router/main.jac
jac_client/examples/basic-full-stack/main.jac
jac_client/examples/css-styling/js-styling/main.jac
jac_client/examples/css-styling/material-ui/main.jac
jac_client/examples/css-styling/pure-css/main.jac
jac_client-0.2.13.dist-info/METADATA
jac_client-0.2.13.dist-info/WHEEL
jac_client-0.2.13.dist-info/entry_points.txt
jac_client-0.2.13.dist-info/top_level.txt
jac_client-0.2.13.dist-info/RECORD
