Metadata-Version: 2.4
Name: jac-client
Version: 0.2.13
Summary: Build full-stack web applications with Jac - one language for frontend and backend.
Author-email: Jason Mars <jason@mars.ninja>
Maintainer-email: Jason Mars <jason@mars.ninja>
License-Expression: MIT
Project-URL: Repository, https://github.com/Jaseci-Labs/jaseci
Project-URL: Homepage, https://jaseci.org
Project-URL: Documentation, https://jac-lang.org
Keywords: jac,jaclang,jaseci,frontend,full-stack,web-development
Requires-Python: >=3.12
Requires-Dist: jaclang>=0.9.13
Provides-Extra: dev
Requires-Dist: python-dotenv==1.0.1; extra == "dev"
Requires-Dist: pytest==8.3.5; extra == "dev"
